README.rst
pyproject.toml
setup.py
bssenv.egg-info/PKG-INFO
bssenv.egg-info/SOURCES.txt
bssenv.egg-info/dependency_links.txt
bssenv.egg-info/entry_points.txt
bssenv.egg-info/top_level.txt
src/comarch/bss/bssenv/__init__.py
src/comarch/bss/bssenv/bssenv.py
src/comarch/bss/bssenv/data/certificates/12125d03.0
src/comarch/bss/bssenv/data/certificates/66808c77.0
src/comarch/bss/bssenv/data/certificates/7605dfdf.0
src/comarch/bss/bssenv/data/certificates/README
src/comarch/bss/bssenv/data/certificates/comarch_root.crt
src/comarch/bss/bssenv/data/certificates/comarch_servers.crt
src/comarch/bss/bssenv/data/certificates/da3b64ee.0
src/comarch/bss/bssenv/data/composefiles/commands/.gitkeep
src/comarch/bss/bssenv/data/composefiles/data_providers/.gitkeep
src/comarch/bss/bssenv/data/config/.gitkeep
src/comarch/bss/bssenv/data/python_site_packages/requirements.txt
src/comarch/bss/bssenv/data/resources/info
src/comarch/bss/bssenv/data/resources/info2
src/comarch/bss/bssenv/data/resources/post_create_environment_from_snap_info
src/comarch/bss/bssenv/data/resources/post_create_environment_info
src/comarch/bss/bssenv/data/scripts/autocompletion/autocomplete.install
src/comarch/bss/bssenv/data/scripts/autocompletion/autocomplete.uninstall
src/comarch/bss/bssenv/data/scripts/bin/activate
src/comarch/bss/bssenv/data/scripts/bin/clean
src/comarch/bss/bssenv/data/scripts/bin/cmd
src/comarch/bss/bssenv/data/scripts/bin/configMaps
src/comarch/bss/bssenv/data/scripts/bin/debug
src/comarch/bss/bssenv/data/scripts/bin/describe
src/comarch/bss/bssenv/data/scripts/bin/dns
src/comarch/bss/bssenv/data/scripts/bin/enter
src/comarch/bss/bssenv/data/scripts/bin/exp
src/comarch/bss/bssenv/data/scripts/bin/fullInstall
src/comarch/bss/bssenv/data/scripts/bin/fullUpdate
src/comarch/bss/bssenv/data/scripts/bin/images
src/comarch/bss/bssenv/data/scripts/bin/init
src/comarch/bss/bssenv/data/scripts/bin/install
src/comarch/bss/bssenv/data/scripts/bin/logs
src/comarch/bss/bssenv/data/scripts/bin/pause
src/comarch/bss/bssenv/data/scripts/bin/ports
src/comarch/bss/bssenv/data/scripts/bin/retagStableDescriptorForImage
